<annotation>
	<folder></folder>
	<filename>maksssksksss91_jpg.rf.4fe9160e5f9cdf1372d3b3a34e170149.jpg</filename>
	<path>maksssksksss91_jpg.rf.4fe9160e5f9cdf1372d3b3a34e170149.jpg</path>
	<source>
		<database>roboflow.com</database>
	</source>
	<size>
		<width>640</width>
		<height>640</height>
		<depth>3</depth>
	</size>
	<segmented>0</segmented>
	<object>
		<name>with_mask</name>
		<pose>Unspecified</pose>
		<truncated>0</truncated>
		<difficult>0</difficult>
		<occluded>0</occluded>
		<bndbox>
			<xmin>99</xmin>
			<xmax>153</xmax>
			<ymin>30</ymin>
			<ymax>146</ymax>
		</bndbox>
	</object>
	<object>
		<name>with_mask</name>
		<pose>Unspecified</pose>
		<truncated>0</truncated>
		<difficult>0</difficult>
		<occluded>0</occluded>
		<bndbox>
			<xmin>177</xmin>
			<xmax>270</xmax>
			<ymin>135</ymin>
			<ymax>325</ymax>
		</bndbox>
	</object>
	<object>
		<name>with_mask</name>
		<pose>Unspecified</pose>
		<truncated>0</truncated>
		<difficult>0</difficult>
		<occluded>0</occluded>
		<bndbox>
			<xmin>319</xmin>
			<xmax>396</xmax>
			<ymin>1</ymin>
			<ymax>120</ymax>
		</bndbox>
	</object>
	<object>
		<name>with_mask</name>
		<pose>Unspecified</pose>
		<truncated>0</truncated>
		<difficult>0</difficult>
		<occluded>0</occluded>
		<bndbox>
			<xmin>390</xmin>
			<xmax>487</xmax>
			<ymin>183</ymin>
			<ymax>399</ymax>
		</bndbox>
	</object>
	<object>
		<name>with_mask</name>
		<pose>Unspecified</pose>
		<truncated>0</truncated>
		<difficult>0</difficult>
		<occluded>0</occluded>
		<bndbox>
			<xmin>464</xmin>
			<xmax>547</xmax>
			<ymin>286</ymin>
			<ymax>525</ymax>
		</bndbox>
	</object>
</annotation>
