<annotation>
	<folder></folder>
	<filename>maksssksksss452_jpg.rf.309726e738f2df8e4d964a00aedacb9e.jpg</filename>
	<path>maksssksksss452_jpg.rf.309726e738f2df8e4d964a00aedacb9e.jpg</path>
	<source>
		<database>roboflow.com</database>
	</source>
	<size>
		<width>640</width>
		<height>640</height>
		<depth>3</depth>
	</size>
	<segmented>0</segmented>
	<object>
		<name>with_mask</name>
		<pose>Unspecified</pose>
		<truncated>0</truncated>
		<difficult>0</difficult>
		<occluded>0</occluded>
		<bndbox>
			<xmin>62</xmin>
			<xmax>116</xmax>
			<ymin>116</ymin>
			<ymax>205</ymax>
		</bndbox>
	</object>
	<object>
		<name>with_mask</name>
		<pose>Unspecified</pose>
		<truncated>0</truncated>
		<difficult>0</difficult>
		<occluded>0</occluded>
		<bndbox>
			<xmin>206</xmin>
			<xmax>249</xmax>
			<ymin>145</ymin>
			<ymax>211</ymax>
		</bndbox>
	</object>
	<object>
		<name>with_mask</name>
		<pose>Unspecified</pose>
		<truncated>0</truncated>
		<difficult>0</difficult>
		<occluded>0</occluded>
		<bndbox>
			<xmin>435</xmin>
			<xmax>483</xmax>
			<ymin>174</ymin>
			<ymax>245</ymax>
		</bndbox>
	</object>
</annotation>
